benny_bean_utils/__init__.py
benny_bean_utils/date/__init__.py
benny_bean_utils/date/date_formatter.py
benny_bean_utils/date/date_obtainer.py
benny_bean_utils/date/date_tester.py
benny_bean_utils/string/__init__.py
benny_bean_utils/string/string_formatter.py
benny_bean_utils-1.0.0.dist-info/METADATA
benny_bean_utils-1.0.0.dist-info/WHEEL
benny_bean_utils-1.0.0.dist-info/licenses/LICENSE
benny_bean_utils-1.0.0.dist-info/RECORD
